ivon/__init__.py
ivon/_ivon.py
ivon_opt-0.1.3.dist-info/LICENSE
ivon_opt-0.1.3.dist-info/METADATA
ivon_opt-0.1.3.dist-info/WHEEL
ivon_opt-0.1.3.dist-info/top_level.txt
ivon_opt-0.1.3.dist-info/RECORD
