Metadata-Version: 2.1
Name: ivon-opt
Version: 0.1.3
Summary: An optimizer for neural networks based on variational learning
Home-page: https://github.com/team-approx-bayes/ivon
Author: IVON Team
Author-email: ivonteam@googlegroups.com
License: GPLv3+
Classifier: Programming Language :: Python :: 3
Classifier: License :: OSI Approved :: GNU General Public License v3 or later (GPLv3+)
Classifier: Operating System :: OS Independent
Requires-Python: >=3.8
License-File: LICENSE
